swh/loader/bzr/__init__.py
swh/loader/bzr/loader.py
swh/loader/bzr/py.typed
swh/loader/bzr/tasks.py
swh/loader/bzr/tests/__init__.py
swh/loader/bzr/tests/conftest.py
swh/loader/bzr/tests/py.typed
swh/loader/bzr/tests/test_loader.py
swh/loader/bzr/tests/test_tasks.py
swh_loader_bzr-1.4.6.dist-info/licenses/AUTHORS
swh_loader_bzr-1.4.6.dist-info/licenses/LICENSE
swh_loader_bzr-1.4.6.dist-info/METADATA
swh_loader_bzr-1.4.6.dist-info/WHEEL
swh_loader_bzr-1.4.6.dist-info/entry_points.txt
swh_loader_bzr-1.4.6.dist-info/top_level.txt
swh_loader_bzr-1.4.6.dist-info/RECORD
